{"is_source_file": false, "format": "", "description": "", "external_files": [], "external_methods": [], "published": [], "classes": [], "methods": [], "calls": [], "search-terms": [], "state": 2, "file_id": 1, "knowledge_revision": 38, "git_revision": "14f7a4d4d763476499ca4806fa2f27fd40998aec", "revision_history": [{"14": "14f7a4d4d763476499ca4806fa2f27fd40998aec"}, {"38": "14f7a4d4d763476499ca4806fa2f27fd40998aec"}], "hash": "2e3c347404b7e9c36df134278c423f73", "format-version": 4, "code-base-name": "Backend", "filename": "README.md"}